sphinx_veldus_theme/__init__.py
sphinx_veldus_theme/breadcrumbs.html
sphinx_veldus_theme/footer.html
sphinx_veldus_theme/layout.html
sphinx_veldus_theme/search.html
sphinx_veldus_theme/searchbox.html
sphinx_veldus_theme/theme.conf
sphinx_veldus_theme/versions.html
sphinx_veldus_theme/locale/sphinx.pot
sphinx_veldus_theme/locale/de/LC_MESSAGES/sphinx.mo
sphinx_veldus_theme/locale/de/LC_MESSAGES/sphinx.po
sphinx_veldus_theme/locale/en/LC_MESSAGES/sphinx.mo
sphinx_veldus_theme/locale/en/LC_MESSAGES/sphinx.po
sphinx_veldus_theme/locale/es/LC_MESSAGES/sphinx.mo
sphinx_veldus_theme/locale/es/LC_MESSAGES/sphinx.po
sphinx_veldus_theme/locale/et/LC_MESSAGES/sphinx.mo
sphinx_veldus_theme/locale/et/LC_MESSAGES/sphinx.po
sphinx_veldus_theme/locale/fr/LC_MESSAGES/sphinx.mo
sphinx_veldus_theme/locale/fr/LC_MESSAGES/sphinx.po
sphinx_veldus_theme/locale/nl/LC_MESSAGES/sphinx.mo
sphinx_veldus_theme/locale/nl/LC_MESSAGES/sphinx.po
sphinx_veldus_theme/locale/pt_BR/LC_MESSAGES/sphinx.mo
sphinx_veldus_theme/locale/pt_BR/LC_MESSAGES/sphinx.po
sphinx_veldus_theme/locale/ru/LC_MESSAGES/sphinx.mo
sphinx_veldus_theme/locale/ru/LC_MESSAGES/sphinx.po
sphinx_veldus_theme/locale/sv/LC_MESSAGES/sphinx.mo
sphinx_veldus_theme/locale/sv/LC_MESSAGES/sphinx.po
sphinx_veldus_theme/locale/tr/LC_MESSAGES/sphinx.mo
sphinx_veldus_theme/locale/tr/LC_MESSAGES/sphinx.po
sphinx_veldus_theme/locale/zh_CN/LC_MESSAGES/sphinx.mo
sphinx_veldus_theme/locale/zh_CN/LC_MESSAGES/sphinx.po
sphinx_veldus_theme/static/css/badge_only.css
sphinx_veldus_theme/static/css/theme.css
sphinx_veldus_theme/static/css/fonts/Roboto-Slab-Bold.woff
sphinx_veldus_theme/static/css/fonts/Roboto-Slab-Bold.woff2
sphinx_veldus_theme/static/css/fonts/Roboto-Slab-Regular.woff
sphinx_veldus_theme/static/css/fonts/Roboto-Slab-Regular.woff2
sphinx_veldus_theme/static/css/fonts/fontawesome-webfont.eot
sphinx_veldus_theme/static/css/fonts/fontawesome-webfont.svg
sphinx_veldus_theme/static/css/fonts/fontawesome-webfont.ttf
sphinx_veldus_theme-0.0.5.dist-info/LICENSE
sphinx_veldus_theme-0.0.5.dist-info/METADATA
sphinx_veldus_theme-0.0.5.dist-info/WHEEL
sphinx_veldus_theme-0.0.5.dist-info/entry_points.txt
sphinx_veldus_theme-0.0.5.dist-info/top_level.txt
sphinx_veldus_theme-0.0.5.dist-info/RECORD
