Metadata-Version: 2.1
Name: sphinx-veldus-theme
Version: 0.0.5
Summary: Read the Docs theme for Sphinx
Home-page: https://github.com/DukeOfEtiquette/sphinx_veldus_theme
Author: Adam DuQuette
Author-email: duquetteadam@gmail.com
License: MIT
Platform: UNKNOWN
Classifier: Framework :: Sphinx
Classifier: Framework :: Sphinx :: Theme
Classifier: Development Status :: 5 - Production/Stable
Classifier: License :: OSI Approved :: MIT License
Classifier: Environment :: Console
Classifier: Environment :: Web Environment
Classifier: Intended Audience :: Developers
Classifier: Programming Language :: Python :: 2.7
Classifier: Programming Language :: Python :: 3
Classifier: Programming Language :: Python :: 3.3
Classifier: Programming Language :: Python :: 3.4
Classifier: Programming Language :: Python :: 3.5
Classifier: Programming Language :: Python :: 3.6
Classifier: Operating System :: OS Independent
Classifier: Topic :: Documentation
Classifier: Topic :: Software Development :: Documentation
Requires-Dist: sphinx
Provides-Extra: dev
Requires-Dist: transifex-client ; extra == 'dev'
Requires-Dist: sphinxcontrib-httpdomain ; extra == 'dev'
Requires-Dist: bump2version ; extra == 'dev'
